py2of/__init__.py
py2of/__main__.py
py2of/domain/__init__.py
py2of/domain/dimensions.py
py2of/domain/of_dict.py
py2of/domain/of_list.py
py2of/domain/of_tensor.py
py2of/domain/of_vector.py
py2of/logging.py
py2of/logging.yaml
py2of/py.typed
py2of/service/__init__.py
py2of/service/case_dumper.py
py2of/service/dumper.py
py2of-0.1.1.dist-info/entry_points.txt
py2of-0.1.1.dist-info/LICENSE
py2of-0.1.1.dist-info/WHEEL
py2of-0.1.1.dist-info/METADATA
py2of-0.1.1.dist-info/RECORD
