Metadata-Version: 2.1
Name: py2of
Version: 0.1.1
Summary: Ultimate PyFoam
Home-page: https://github.com/ziky5/py2of
License: MIT
Author: Petr Zikan
Author-email: zikan.p@gmail.com
Requires-Python: >=3.7,<4.0
Classifier: Development Status :: 1 - Planning
Classifier: License :: OSI Approved :: MIT License
Classifier: Programming Language :: Python :: 3
Classifier: Programming Language :: Python :: 3.7
Classifier: Programming Language :: Python :: 3.8
Classifier: Programming Language :: Python :: 3.9
Classifier: Programming Language :: Python :: 3.10
Requires-Dist: click (>=8.0.1)
Requires-Dist: coloredlogs (>=15.0.1,<16.0.0)
Project-URL: Changelog, https://github.com/ziky5/py2of/releases
Project-URL: Documentation, https://py2of.readthedocs.io
Project-URL: Repository, https://github.com/ziky5/py2of
